cloudyns/__init__.py
cloudyns/pre_soft.py
cloudyns-0.0.1.dist-info/LICENSE
cloudyns-0.0.1.dist-info/METADATA
cloudyns-0.0.1.dist-info/WHEEL
cloudyns-0.0.1.dist-info/top_level.txt
cloudyns-0.0.1.dist-info/RECORD
